{
  "version": "5.3.1",
  "flags": {},
  "shapes": [
    {
      "label": "Blast pad/ Stopway",
      "points": [
        [
          1573.5802469135801,
          369.6296296296296
        ],
        [
          1577.2839506172838,
          716.5432098765432
        ],
        [
          1822.9629629629628,
          717.7777777777777
        ],
        [
          1819.2592592592591,
          373.3333333333333
        ]
      ],
      "group_id": null,
      "description": "",
      "shape_type": "polygon",
      "flags": {}
    },
    {
      "label": "Runway Marking",
      "points": [
        [
          1241.4814814814813,
          500.4938271604938
        ],
        [
          1245.185185185185,
          577.0370370370371
        ],
        [
          1398.2716049382714,
          575.8024691358024
        ],
        [
          1395.8024691358023,
          499.25925925925924
        ]
      ],
      "group_id": null,
      "description": "",
      "shape_type": "polygon",
      "flags": {}
    },
    {
      "label": "Runway",
      "points": [
        [
          0.7407407407407689,
          432.5925925925926
        ],
        [
          0.0,
          506.296296296299
        ],
        [
          0.0,
          677.0370370370371
        ],
        [
          1568.6419753086418,
          663.4567901234568
        ],
        [
          1566.1728395061727,
          421.48148148148147
        ]
      ],
      "group_id": null,
      "description": "",
      "shape_type": "polygon",
      "flags": {}
    },
    {
      "label": "Taxiway",
      "points": [
        [
          427.9012345679012,
          1.7283950617284365
        ],
        [
          443.9506172839506,
          52.34567901234572
        ],
        [
          452.59259259259255,
          175.80246913580248
        ],
        [
          441.48148148148147,
          293.08641975308643
        ],
        [
          421.72839506172835,
          360.98765432098764
        ],
        [
          368.641975308642,
          423.95061728395063
        ],
        [
          677.283950617284,
          422.71604938271605
        ],
        [
          627.9012345679013,
          363.4567901234568
        ],
        [
          601.9753086419753,
          298.0246913580247
        ],
        [
          594.5679012345679,
          165.92592592592598
        ],
        [
          599.5061728395062,
          57.28395061728399
        ],
        [
          615.5555555555555,
          0.4938271604938693
        ]
      ],
      "group_id": null,
      "description": "",
      "shape_type": "polygon",
      "flags": {}
    },
    {
      "label": "Taxiway",
      "points": [
        [
          1427.9012345679012,
          2.9629629629630045
        ],
        [
          1443.9506172839506,
          46.17283950617288
        ],
        [
          1451.358024691358,
          165.92592592592598
        ],
        [
          1443.9506172839506,
          289.38271604938274
        ],
        [
          1418.0246913580245,
          351.11111111111114
        ],
        [
          1371.1111111111109,
          414.0740740740741
        ],
        [
          1569.8765432098764,
          410.3703703703704
        ],
        [
          1571.1111111111109,
          346.17283950617286
        ],
        [
          1574.8148148148146,
          0.4938271604938693
        ]
      ],
      "group_id": null,
      "description": "",
      "shape_type": "polygon",
      "flags": {}
    }
  ],
  "imagePath": "14.jpg",
  "imageData": null,
  "imageHeight": 1080,
  "imageWidth": 1920
}