{
  "version": "5.3.1",
  "flags": {},
  "shapes": [
    {
      "label": "Blast pad/ Stopway",
      "points": [
        [
          1337.7777777777776,
          256.04938271604937
        ],
        [
          1343.9506172839506,
          483.2098765432099
        ],
        [
          1919.0,
          488.1353530546964
        ],
        [
          1913.0864197530861,
          256.04938271604937
        ]
      ],
      "group_id": null,
      "description": "",
      "shape_type": "polygon",
      "flags": {}
    },
    {
      "label": "Runway Marking",
      "points": [
        [
          1121.7283950617282,
          342.46913580246917
        ],
        [
          1121.7283950617282,
          395.55555555555554
        ],
        [
          1219.2592592592591,
          393.08641975308643
        ],
        [
          1216.79012345679,
          340.0
        ]
      ],
      "group_id": null,
      "description": "",
      "shape_type": "polygon",
      "flags": {}
    },
    {
      "label": "Runway",
      "points": [
        [
          0.7407407407407689,
          310.3703703703704
        ],
        [
          0.7407407407407689,
          426.41975308641975
        ],
        [
          1334.074074074074,
          430.12345679012344
        ],
        [
          1332.8395061728393,
          314.0740740740741
        ]
      ],
      "group_id": null,
      "description": "",
      "shape_type": "polygon",
      "flags": {}
    },
    {
      "label": "Taxiway",
      "points": [
        [
          1197.037037037037,
          436.2962962962963
        ],
        [
          1339.0123456790122,
          437.5308641975309
        ],
        [
          1339.0123456790122,
          490.61728395061726
        ],
        [
          1345.185185185185,
          553.5802469135803
        ],
        [
          1348.8888888888887,
          727.6543209876543
        ],
        [
          1350.1234567901233,
          753.5802469135803
        ],
        [
          1334.074074074074,
          804.1975308641975
        ],
        [
          1305.679012345679,
          851.1111111111111
        ],
        [
          1277.2839506172838,
          878.2716049382716
        ],
        [
          1241.4814814814813,
          904.1975308641975
        ],
        [
          1201.9753086419753,
          914.074074074074
        ],
        [
          1174.8148148148148,
          921.4814814814814
        ],
        [
          1018.0246913580246,
          920.2469135802469
        ],
        [
          0.0,
          914.1582491582491
        ],
        [
          0.0,
          848.6419753086419
        ],
        [
          764.9382716049383,
          852.3456790123456
        ],
        [
          884.6913580246913,
          848.6419753086419
        ],
        [
          966.1728395061729,
          844.9382716049382
        ],
        [
          1058.7654320987654,
          835.0617283950617
        ],
        [
          1127.9012345679012,
          814.074074074074
        ],
        [
          1172.3456790123455,
          785.679012345679
        ],
        [
          1203.2098765432097,
          760.9876543209876
        ],
        [
          1226.6666666666665,
          731.358024691358
        ],
        [
          1246.4197530864196,
          693.0864197530864
        ],
        [
          1263.7037037037035,
          652.3456790123456
        ],
        [
          1267.4074074074072,
          606.6666666666666
        ],
        [
          1268.6419753086418,
          565.9259259259259
        ],
        [
          1261.2345679012344,
          525.1851851851852
        ],
        [
          1250.1234567901233,
          486.91358024691357
        ],
        [
          1226.6666666666665,
          451.1111111111111
        ]
      ],
      "group_id": null,
      "description": "",
      "shape_type": "polygon",
      "flags": {}
    }
  ],
  "imagePath": "204.jpg",
  "imageData": null,
  "imageHeight": 1080,
  "imageWidth": 1920
}