{
  "version": "5.3.1",
  "flags": {},
  "shapes": [
    {
      "label": "Buildings",
      "points": [
        [
          1689.6296296296296,
          1.7283950617284365
        ],
        [
          1671.1198082389374,
          1079.0
        ],
        [
          1919.0,
          1077.1320252882838
        ],
        [
          1919.0,
          4.197530864197573
        ]
      ],
      "group_id": null,
      "description": "",
      "shape_type": "polygon",
      "flags": {}
    },
    {
      "label": "Parking Stand Area",
      "points": [
        [
          3.2098765432099015,
          607.9012345679013
        ],
        [
          21.728395061728428,
          620.2469135802469
        ],
        [
          137.7777777777778,
          583.2098765432098
        ],
        [
          176.0493827160494,
          694.320987654321
        ],
        [
          71.11111111111114,
          730.1234567901234
        ],
        [
          0.0,
          893.1320037986704
        ]
      ],
      "group_id": null,
      "description": "",
      "shape_type": "polygon",
      "flags": {}
    },
    {
      "label": "Parking Stand Area",
      "points": [
        [
          213.08641975308646,
          815.3086419753087
        ],
        [
          148.8888888888889,
          835.0617283950617
        ],
        [
          48.88888888888891,
          794.320987654321
        ],
        [
          0.0,
          903.4682744760264
        ],
        [
          1.9753086419753387,
          1030.1234567901233
        ],
        [
          145.18518518518522,
          978.2716049382716
        ],
        [
          171.11111111111114,
          905.4320987654321
        ],
        [
          215.55555555555557,
          890.6172839506172
        ]
      ],
      "group_id": null,
      "description": "",
      "shape_type": "polygon",
      "flags": {}
    },
    {
      "label": "Parking Stand Area",
      "points": [
        [
          647.6543209876544,
          788.1481481481482
        ],
        [
          474.81481481481484,
          784.4444444444445
        ],
        [
          404.4444444444444,
          847.4074074074074
        ],
        [
          369.8765432098765,
          847.4074074074074
        ],
        [
          366.1728395061728,
          959.753086419753
        ],
        [
          405.679012345679,
          960.9876543209876
        ],
        [
          476.04938271604937,
          1023.9506172839506
        ],
        [
          645.1851851851852,
          1026.4197530864196
        ]
      ],
      "group_id": null,
      "description": "",
      "shape_type": "polygon",
      "flags": {}
    },
    {
      "label": "Parking Stand Area",
      "points": [
        [
          653.8271604938271,
          131.35802469135808
        ],
        [
          418.02469135802465,
          130.1234567901235
        ],
        [
          279.75308641975306,
          243.70370370370375
        ],
        [
          208.14814814814818,
          244.93827160493828
        ],
        [
          208.14814814814818,
          360.98765432098764
        ],
        [
          283.45679012345676,
          362.22222222222223
        ],
        [
          413.0864197530864,
          479.5061728395062
        ],
        [
          643.9506172839507,
          483.2098765432099
        ]
      ],
      "group_id": null,
      "description": "",
      "shape_type": "polygon",
      "flags": {}
    },
    {
      "label": "Parking Stand Area",
      "points": [
        [
          1583.4567901234566,
          211.60493827160496
        ],
        [
          1480.9876543209875,
          202.962962962963
        ],
        [
          1410.617283950617,
          125.1851851851852
        ],
        [
          1164.938271604938,
          123.95061728395065
        ],
        [
          1164.938271604938,
          363.4567901234568
        ],
        [
          1403.2098765432097,
          364.69135802469134
        ],
        [
          1476.0493827160492,
          289.38271604938274
        ],
        [
          1582.2222222222222,
          293.08641975308643
        ]
      ],
      "group_id": null,
      "description": "",
      "shape_type": "polygon",
      "flags": {}
    },
    {
      "label": "Parking Stand Area",
      "points": [
        [
          1582.2222222222222,
          489.38271604938274
        ],
        [
          1497.037037037037,
          484.44444444444446
        ],
        [
          1404.4444444444443,
          372.0987654320988
        ],
        [
          1163.7037037037035,
          369.6296296296296
        ],
        [
          1158.7654320987654,
          753.5802469135803
        ],
        [
          1309.3827160493827,
          752.3456790123456
        ],
        [
          1351.358024691358,
          752.3456790123456
        ],
        [
          1490.864197530864,
          698.0246913580247
        ],
        [
          1541.4814814814813,
          673.3333333333334
        ],
        [
          1580.9876543209875,
          621.4814814814815
        ]
      ],
      "group_id": null,
      "description": "",
      "shape_type": "polygon",
      "flags": {}
    },
    {
      "label": "Parking Stand Area",
      "points": [
        [
          1562.469135802469,
          940.0
        ],
        [
          1462.469135802469,
          952.3456790123456
        ],
        [
          1352.5925925925924,
          809.1358024691358
        ],
        [
          1156.296296296296,
          805.4320987654321
        ],
        [
          1147.747299382716,
          1079.0
        ],
        [
          1411.8518518518517,
          1079.0
        ],
        [
          1468.6419753086418,
          1044.9382716049383
        ],
        [
          1562.469135802469,
          1043.7037037037037
        ]
      ],
      "group_id": null,
      "description": "",
      "shape_type": "polygon",
      "flags": {}
    },
    {
      "label": "Apron",
      "points": [
        [
          1683.4567901234566,
          2.9629629629630045
        ],
        [
          0.7407407407407689,
          0.4938271604938693
        ],
        [
          0.7407407407407689,
          600.4938271604938
        ],
        [
          20.493827160493858,
          612.8395061728395
        ],
        [
          142.71604938271608,
          575.8024691358024
        ],
        [
          183.4567901234568,
          696.7901234567901
        ],
        [
          74.81481481481484,
          736.2962962962963
        ],
        [
          50.12345679012348,
          789.3827160493827
        ],
        [
          151.35802469135805,
          828.8888888888889
        ],
        [
          216.79012345679016,
          809.1358024691358
        ],
        [
          222.96296296296296,
          894.3209876543209
        ],
        [
          173.58024691358028,
          911.6049382716049
        ],
        [
          151.35802469135805,
          983.2098765432098
        ],
        [
          0.0,
          1038.5847636254139
        ],
        [
          0.0,
          1079.0
        ],
        [
          637.7777777777778,
          1078.2716049382716
        ],
        [
          641.4814814814815,
          1032.5925925925926
        ],
        [
          471.11111111111103,
          1030.1234567901233
        ],
        [
          403.2098765432099,
          968.395061728395
        ],
        [
          361.2345679012345,
          965.9259259259259
        ],
        [
          363.7037037037037,
          842.469135802469
        ],
        [
          400.7407407407407,
          841.2345679012345
        ],
        [
          471.11111111111103,
          779.5061728395061
        ],
        [
          653.8271604938271,
          779.5061728395061
        ],
        [
          650.1234567901234,
          1030.1234567901233
        ],
        [
          641.5700617283951,
          1079.0
        ],
        [
          1141.4814814814813,
          1079.0
        ],
        [
          1151.358024691358,
          801.7283950617284
        ],
        [
          1153.827160493827,
          752.3456790123456
        ],
        [
          1157.5308641975307,
          367.1604938271605
        ],
        [
          1158.7654320987654,
          123.95061728395065
        ],
        [
          660.0,
          132.5925925925926
        ],
        [
          646.4197530864197,
          488.14814814814815
        ],
        [
          404.4444444444444,
          484.44444444444446
        ],
        [
          280.98765432098764,
          369.6296296296296
        ],
        [
          201.97530864197532,
          365.9259259259259
        ],
        [
          201.97530864197532,
          238.76543209876547
        ],
        [
          276.04938271604937,
          237.5308641975309
        ],
        [
          418.02469135802465,
          123.95061728395065
        ],
        [
          656.2962962962963,
          126.41975308641979
        ],
        [
          1167.4074074074074,
          119.01234567901238
        ],
        [
          1416.79012345679,
          119.01234567901238
        ],
        [
          1484.6913580246912,
          195.5555555555556
        ],
        [
          1589.6296296296296,
          206.66666666666669
        ],
        [
          1587.1604938271603,
          298.0246913580247
        ],
        [
          1480.9876543209875,
          295.55555555555554
        ],
        [
          1410.617283950617,
          367.1604938271605
        ],
        [
          1498.2716049382714,
          477.037037037037
        ],
        [
          1588.395061728395,
          484.44444444444446
        ],
        [
          1585.9259259259259,
          626.4197530864197
        ],
        [
          1545.185185185185,
          679.5061728395061
        ],
        [
          1493.3333333333333,
          706.6666666666666
        ],
        [
          1355.0617283950617,
          759.7530864197531
        ],
        [
          1310.617283950617,
          758.5185185185185
        ],
        [
          1161.2345679012344,
          760.9876543209876
        ],
        [
          1157.5308641975307,
          798.0246913580247
        ],
        [
          1355.0617283950617,
          802.9629629629629
        ],
        [
          1462.469135802469,
          942.469135802469
        ],
        [
          1568.6419753086418,
          933.8271604938271
        ],
        [
          1567.4074074074072,
          1047.4074074074074
        ],
        [
          1474.8148148148146,
          1052.3456790123457
        ],
        [
          1422.616769547325,
          1079.0
        ],
        [
          1666.1728395061727,
          1079.0
        ]
      ],
      "group_id": null,
      "description": "",
      "shape_type": "polygon",
      "flags": {}
    }
  ],
  "imagePath": "172.jpg",
  "imageData": null,
  "imageHeight": 1080,
  "imageWidth": 1920
}