{
  "version": "5.3.1",
  "flags": {},
  "shapes": [
    {
      "label": "Blast pad/ Stopway",
      "points": [
        [
          663.6276595744681,
          696.7234042553191
        ],
        [
          662.5638297872341,
          921.1914893617021
        ],
        [
          1061.5,
          919.063829787234
        ],
        [
          1058.3085106382978,
          696.7234042553191
        ]
      ],
      "group_id": null,
      "description": "",
      "shape_type": "polygon",
      "flags": {}
    },
    {
      "label": "Runway Marking",
      "points": [
        [
          293.41489361702133,
          761.6170212765958
        ],
        [
          287.03191489361706,
          870.1276595744681
        ],
        [
          449.79787234042556,
          859.4893617021277
        ],
        [
          452.9893617021277,
          768.0
        ]
      ],
      "group_id": null,
      "description": "",
      "shape_type": "polygon",
      "flags": {}
    },
    {
      "label": "Runway",
      "points": [
        [
          0.8617021276596404,
          740.3404255319149
        ],
        [
          0.8617021276596404,
          890.3404255319149
        ],
        [
          656.1808510638299,
          886.0851063829787
        ],
        [
          654.0531914893618,
          736.0851063829787
        ]
      ],
      "group_id": null,
      "description": "",
      "shape_type": "polygon",
      "flags": {}
    },
    {
      "label": "Taxiway",
      "points": [
        [
          0.8617021276596404,
          375.44680851063833
        ],
        [
          2.9893617021277237,
          458.4255319148936
        ],
        [
          72.13829787234047,
          463.74468085106383
        ],
        [
          166.81914893617025,
          469.06382978723406
        ],
        [
          214.69148936170217,
          481.82978723404256
        ],
        [
          246.60638297872345,
          504.17021276595744
        ],
        [
          260.436170212766,
          529.7021276595744
        ],
        [
          271.07446808510645,
          565.8723404255319
        ],
        [
          271.07446808510645,
          639.2765957446809
        ],
        [
          255.11702127659578,
          687.1489361702128
        ],
        [
          240.22340425531917,
          709.4893617021277
        ],
        [
          217.88297872340428,
          725.4468085106383
        ],
        [
          189.15957446808514,
          733.9574468085107
        ],
        [
          659.372340425532,
          729.7021276595744
        ],
        [
          659.372340425532,
          691.4042553191489
        ],
        [
          668.9468085106383,
          688.2127659574468
        ],
        [
          681.7127659574469,
          596.7234042553191
        ],
        [
          689.1595744680852,
          556.2978723404256
        ],
        [
          700.8617021276597,
          536.0851063829787
        ],
        [
          720.0106382978724,
          515.8723404255319
        ],
        [
          746.6063829787234,
          506.29787234042556
        ],
        [
          956.1808510638299,
          485.02127659574467
        ],
        [
          998.7340425531914,
          477.5744680851064
        ],
        [
          1032.776595744681,
          477.5744680851064
        ],
        [
          1622.0,
          474.4122673467058
        ],
        [
          1622.0,
          303.1063829787234
        ],
        [
          951.9255319148937,
          303.1063829787234
        ],
        [
          771.0744680851064,
          252.0425531914894
        ],
        [
          307.2446808510639,
          256.29787234042556
        ],
        [
          306.18085106382983,
          299.9148936170213
        ],
        [
          288.0957446808511,
          333.95744680851067
        ],
        [
          256.18085106382983,
          358.4255319148936
        ],
        [
          199.79787234042556,
          372.25531914893617
        ]
      ],
      "group_id": null,
      "description": "",
      "shape_type": "polygon",
      "flags": {}
    },
    {
      "label": "Buildings",
      "points": [
        [
          775.3297872340427,
          3.1063829787234214
        ],
        [
          780.6489361702128,
          75.4468085106383
        ],
        [
          1622.0,
          97.31360596166002
        ],
        [
          1622.0,
          0.0
        ]
      ],
      "group_id": null,
      "description": "",
      "shape_type": "polygon",
      "flags": {}
    },
    {
      "label": "Parking Stand Area",
      "points": [
        [
          595.5425531914894,
          145.6595744680851
        ],
        [
          650.8617021276597,
          224.38297872340428
        ],
        [
          687.0319148936171,
          223.31914893617022
        ],
        [
          722.1382978723404,
          155.2340425531915
        ],
        [
          725.3297872340427,
          89.27659574468086
        ],
        [
          596.6063829787234,
          91.40425531914894
        ]
      ],
      "group_id": null,
      "description": "",
      "shape_type": "polygon",
      "flags": {}
    },
    {
      "label": "Parking Stand Area",
      "points": [
        [
          857.2446808510639,
          111.61702127659575
        ],
        [
          908.3085106382979,
          111.61702127659575
        ],
        [
          923.2021276595746,
          154.17021276595744
        ],
        [
          923.2021276595746,
          260.5531914893617
        ],
        [
          827.4574468085107,
          235.02127659574467
        ],
        [
          828.5212765957448,
          160.55319148936172
        ]
      ],
      "group_id": null,
      "description": "",
      "shape_type": "polygon",
      "flags": {}
    },
    {
      "label": "Parking Stand Area",
      "points": [
        [
          980.6489361702128,
          115.87234042553193
        ],
        [
          1035.968085106383,
          118.00000000000001
        ],
        [
          1054.0531914893616,
          175.44680851063828
        ],
        [
          1055.1170212765958,
          276.51063829787233
        ],
        [
          966.8191489361703,
          276.51063829787233
        ],
        [
          930.6489361702128,
          262.6808510638298
        ],
        [
          928.5212765957448,
          155.2340425531915
        ]
      ],
      "group_id": null,
      "description": "",
      "shape_type": "polygon",
      "flags": {}
    },
    {
      "label": "Parking Stand Area",
      "points": [
        [
          1059.3723404255318,
          88.21276595744682
        ],
        [
          1043.414893617021,
          113.74468085106383
        ],
        [
          1059.3723404255318,
          174.38297872340428
        ],
        [
          1063.627659574468,
          274.3829787234043
        ],
        [
          1227.4574468085107,
          278.63829787234044
        ],
        [
          1206.1808510638298,
          106.29787234042554
        ],
        [
          1117.8829787234042,
          115.87234042553193
        ]
      ],
      "group_id": null,
      "description": "",
      "shape_type": "polygon",
      "flags": {}
    },
    {
      "label": "Apron",
      "points": [
        [
          1621.0744680851062,
          102.04255319148938
        ],
        [
          1621.0744680851062,
          295.6595744680851
        ],
        [
          950.8617021276597,
          297.7872340425532
        ],
        [
          772.1382978723404,
          245.6595744680851
        ],
        [
          0.0,
          247.77212795063593
        ],
        [
          0.0,
          0.0
        ],
        [
          767.8829787234043,
          0.9787234042553363
        ],
        [
          774.2659574468086,
          78.63829787234044
        ],
        [
          732.7765957446809,
          85.0212765957447
        ],
        [
          589.1595744680852,
          87.14893617021278
        ],
        [
          588.0957446808511,
          150.97872340425533
        ],
        [
          648.7340425531916,
          230.7659574468085
        ],
        [
          695.5425531914894,
          228.63829787234044
        ],
        [
          727.4574468085107,
          157.36170212765956
        ],
        [
          734.904255319149,
          92.46808510638299
        ],
        [
          783.840425531915,
          81.82978723404257
        ],
        [
          1050.8617021276596,
          87.14893617021278
        ],
        [
          1035.968085106383,
          110.55319148936171
        ],
        [
          977.4574468085108,
          110.55319148936171
        ],
        [
          928.5212765957448,
          147.78723404255322
        ],
        [
          909.372340425532,
          104.17021276595746
        ],
        [
          851.9255319148937,
          106.29787234042554
        ],
        [
          823.2021276595746,
          157.36170212765956
        ],
        [
          822.1382978723404,
          238.21276595744683
        ],
        [
          924.2659574468086,
          266.93617021276594
        ],
        [
          966.8191489361703,
          282.8936170212766
        ],
        [
          1061.5,
          279.7021276595745
        ],
        [
          1234.904255319149,
          282.8936170212766
        ],
        [
          1211.5,
          100.97872340425533
        ],
        [
          1118.9468085106382,
          110.55319148936171
        ],
        [
          1065.755319148936,
          86.08510638297874
        ]
      ],
      "group_id": null,
      "description": "",
      "shape_type": "polygon",
      "flags": {}
    }
  ],
  "imagePath": "233.jpg",
  "imageData": null,
  "imageHeight": 936,
  "imageWidth": 1623
}