{
  "version": "5.3.1",
  "flags": {},
  "shapes": [
    {
      "label": "Buildings",
      "points": [
        [
          301.9753086419753,
          1.7283950617284365
        ],
        [
          301.9753086419753,
          211.60493827160496
        ],
        [
          492.0987654320988,
          211.60493827160496
        ],
        [
          492.0987654320988,
          1.7283950617284365
        ]
      ],
      "group_id": null,
      "description": "",
      "shape_type": "polygon",
      "flags": {}
    },
    {
      "label": "Buildings",
      "points": [
        [
          663.7037037037037,
          1.7283950617284365
        ],
        [
          660.0,
          277.03703703703707
        ],
        [
          1871.1111111111109,
          270.8641975308642
        ],
        [
          1872.3367409641917,
          0.0
        ]
      ],
      "group_id": null,
      "description": "",
      "shape_type": "polygon",
      "flags": {}
    },
    {
      "label": "Parking Stand Area",
      "points": [
        [
          934.074074074074,
          327.65432098765433
        ],
        [
          932.8395061728395,
          373.3333333333333
        ],
        [
          858.7654320987655,
          430.12345679012344
        ],
        [
          860.0,
          649.8765432098766
        ],
        [
          1068.6419753086418,
          651.1111111111111
        ],
        [
          1064.938271604938,
          426.41975308641975
        ],
        [
          1015.5555555555555,
          379.5061728395062
        ],
        [
          1009.3827160493828,
          332.5925925925926
        ]
      ],
      "group_id": null,
      "description": "",
      "shape_type": "polygon",
      "flags": {}
    },
    {
      "label": "Parking Stand Area",
      "points": [
        [
          1119.2592592592591,
          373.3333333333333
        ],
        [
          1177.2839506172838,
          373.3333333333333
        ],
        [
          1221.7283950617282,
          443.7037037037037
        ],
        [
          1218.0246913580245,
          646.1728395061729
        ],
        [
          1072.3456790123455,
          649.8765432098766
        ],
        [
          1069.8765432098764,
          438.7654320987654
        ]
      ],
      "group_id": null,
      "description": "",
      "shape_type": "polygon",
      "flags": {}
    },
    {
      "label": "Parking Stand Area",
      "points": [
        [
          1263.7037037037035,
          340.0
        ],
        [
          1350.1234567901233,
          340.0
        ],
        [
          1392.0987654320986,
          436.2962962962963
        ],
        [
          1398.2716049382714,
          642.4691358024692
        ],
        [
          1224.1975308641975,
          647.4074074074074
        ],
        [
          1229.1358024691356,
          441.2345679012346
        ]
      ],
      "group_id": null,
      "description": "",
      "shape_type": "polygon",
      "flags": {}
    },
    {
      "label": "Parking Stand Area",
      "points": [
        [
          1459.9999999999998,
          390.61728395061726
        ],
        [
          1526.6666666666665,
          385.67901234567904
        ],
        [
          1556.296296296296,
          462.22222222222223
        ],
        [
          1561.2345679012344,
          644.9382716049382
        ],
        [
          1403.2098765432097,
          643.7037037037037
        ],
        [
          1395.8024691358023,
          465.9259259259259
        ]
      ],
      "group_id": null,
      "description": "",
      "shape_type": "polygon",
      "flags": {}
    },
    {
      "label": "Parking Stand Area",
      "points": [
        [
          1582.2222222222222,
          330.12345679012344
        ],
        [
          1663.7037037037035,
          327.65432098765433
        ],
        [
          1706.9135802469134,
          420.24691358024694
        ],
        [
          1715.5555555555554,
          647.4074074074074
        ],
        [
          1567.4074074074072,
          646.1728395061729
        ],
        [
          1558.7654320987654,
          423.95061728395063
        ]
      ],
      "group_id": null,
      "description": "",
      "shape_type": "polygon",
      "flags": {}
    },
    {
      "label": "Parking Stand Area",
      "points": [
        [
          210.6172839506173,
          437.5308641975309
        ],
        [
          206.9135802469136,
          506.66666666666663
        ],
        [
          151.35802469135805,
          556.0493827160494
        ],
        [
          152.5925925925926,
          652.3456790123456
        ],
        [
          279.75308641975306,
          653.5802469135803
        ],
        [
          280.98765432098764,
          507.90123456790127
        ],
        [
          262.4691358024691,
          499.25925925925924
        ],
        [
          261.2345679012346,
          435.0617283950617
        ]
      ],
      "group_id": null,
      "description": "",
      "shape_type": "polygon",
      "flags": {}
    },
    {
      "label": "Parking Stand Area",
      "points": [
        [
          382.22222222222223,
          419.01234567901236
        ],
        [
          432.8395061728395,
          417.77777777777777
        ],
        [
          471.11111111111103,
          481.9753086419753
        ],
        [
          469.8765432098765,
          648.6419753086419
        ],
        [
          339.01234567901236,
          652.3456790123456
        ],
        [
          346.41975308641975,
          479.5061728395062
        ]
      ],
      "group_id": null,
      "description": "",
      "shape_type": "polygon",
      "flags": {}
    },
    {
      "label": "Apron",
      "points": [
        [
          1877.2839506172838,
          0.4938271604938693
        ],
        [
          1877.2839506172838,
          278.2716049382716
        ],
        [
          652.5925925925926,
          281.97530864197535
        ],
        [
          655.0617283950618,
          0.4938271604938693
        ],
        [
          500.7407407407407,
          1.7283950617284365
        ],
        [
          498.27160493827154,
          219.01234567901236
        ],
        [
          295.8024691358025,
          217.77777777777783
        ],
        [
          295.8024691358025,
          0.0
        ],
        [
          139.01234567901238,
          6.666666666666709
        ],
        [
          120.49382716049385,
          307.90123456790127
        ],
        [
          93.33333333333337,
          565.9259259259259
        ],
        [
          147.65432098765436,
          552.3456790123457
        ],
        [
          199.5061728395062,
          504.1975308641975
        ],
        [
          205.679012345679,
          430.12345679012344
        ],
        [
          264.9382716049383,
          428.8888888888889
        ],
        [
          268.641975308642,
          495.55555555555554
        ],
        [
          285.9259259259259,
          502.96296296296293
        ],
        [
          284.69135802469134,
          651.1111111111111
        ],
        [
          334.0740740740741,
          647.4074074074074
        ],
        [
          342.71604938271605,
          474.5679012345679
        ],
        [
          380.98765432098764,
          411.60493827160496
        ],
        [
          436.5432098765432,
          410.3703703703704
        ],
        [
          477.2839506172839,
          481.9753086419753
        ],
        [
          477.2839506172839,
          647.4074074074074
        ],
        [
          853.8271604938271,
          646.1728395061729
        ],
        [
          852.5925925925926,
          427.65432098765433
        ],
        [
          926.6666666666666,
          373.3333333333333
        ],
        [
          927.9012345679013,
          323.95061728395063
        ],
        [
          1015.5555555555555,
          326.41975308641975
        ],
        [
          1022.9629629629629,
          377.03703703703707
        ],
        [
          1072.3456790123455,
          427.65432098765433
        ],
        [
          1116.79012345679,
          367.1604938271605
        ],
        [
          1183.4567901234566,
          367.1604938271605
        ],
        [
          1224.1975308641975,
          435.0617283950617
        ],
        [
          1259.9999999999998,
          331.358024691358
        ],
        [
          1353.827160493827,
          332.5925925925926
        ],
        [
          1398.2716049382714,
          430.12345679012344
        ],
        [
          1400.7407407407406,
          449.87654320987656
        ],
        [
          1458.7654320987654,
          384.44444444444446
        ],
        [
          1529.1358024691356,
          379.5061728395062
        ],
        [
          1555.0617283950617,
          442.4691358024691
        ],
        [
          1555.0617283950617,
          420.24691358024694
        ],
        [
          1579.753086419753,
          321.48148148148147
        ],
        [
          1664.938271604938,
          320.24691358024694
        ],
        [
          1711.8518518518517,
          421.48148148148147
        ],
        [
          1720.4938271604938,
          653.5802469135803
        ],
        [
          1563.7037037037035,
          651.1111111111111
        ],
        [
          1400.7407407407406,
          651.1111111111111
        ],
        [
          1219.2592592592591,
          651.1111111111111
        ],
        [
          1073.5802469135801,
          657.283950617284
        ],
        [
          855.0617283950618,
          652.3456790123456
        ],
        [
          472.34567901234567,
          653.5802469135803
        ],
        [
          337.77777777777777,
          659.7530864197531
        ],
        [
          278.51851851851853,
          660.9876543209876
        ],
        [
          147.65432098765436,
          657.283950617284
        ],
        [
          146.41975308641977,
          559.7530864197531
        ],
        [
          92.09876543209879,
          573.3333333333334
        ],
        [
          72.3456790123457,
          1075.8024691358025
        ],
        [
          1919.0,
          1077.0205788462165
        ],
        [
          1919.0,
          2.9629629629630045
        ]
      ],
      "group_id": null,
      "description": "",
      "shape_type": "polygon",
      "flags": {}
    }
  ],
  "imagePath": "291.jpg",
  "imageData": null,
  "imageHeight": 1080,
  "imageWidth": 1920
}